protonup/__init__.py
protonup/__main__.py
protonup/api.py
protonup/cli.py
protonup/constants.py
protonup/utilities.py
protonup-0.1.5.dist-info/LICENSE
protonup-0.1.5.dist-info/METADATA
protonup-0.1.5.dist-info/WHEEL
protonup-0.1.5.dist-info/entry_points.txt
protonup-0.1.5.dist-info/top_level.txt
protonup-0.1.5.dist-info/RECORD
