Metadata-Version: 2.1
Name: protonup
Version: 0.1.5
Summary: Manage Proton-GE Installations
Home-page: https://github.com/AUNaseef/protonup
Author: Naseef
License: GPL-3.0
Requires-Python: >3.6
License-File: LICENSE
Requires-Dist: requests
Requires-Dist: configparser
